snaplot/__init__.py
snaplot/main.py
snaplot-0.2.0.dist-info/licenses/LICENSE
snaplot-0.2.0.dist-info/METADATA
snaplot-0.2.0.dist-info/WHEEL
snaplot-0.2.0.dist-info/top_level.txt
snaplot-0.2.0.dist-info/RECORD
