Metadata-Version: 2.4
Name: snaplot
Version: 0.2.0
Summary: Record and replay every step of your plotting process
Author-email: Joseph Barbier <joseph.barbierdarnal@gmail.com>
License-Expression: MIT
Project-URL: Homepage, https://y-sunflower.github.io/snaplot/
Project-URL: Issues, https://github.com/y-sunflower/snaplot/issues
Project-URL: Documentation, https://y-sunflower.github.io/snaplot/
Project-URL: Repository, https://github.com/y-sunflower/snaplot
Keywords: matplotlib,record,gif,evolution
Classifier: Programming Language :: Python :: 3
Classifier: Operating System :: OS Independent
Classifier: Development Status :: 4 - Beta
Requires-Python: >=3.9
License-File: LICENSE
Requires-Dist: gifing>=0.1.1
Requires-Dist: matplotlib>=3.9.4
Dynamic: license-file
